_cluster_shapley.cpython-38-darwin.so
dr_explainer/__init__.py
dr_explainer/explainer.py
dr_explainer/plot.py
cluster_shapley-0.1.6.dist-info/LICENSE
cluster_shapley-0.1.6.dist-info/METADATA
cluster_shapley-0.1.6.dist-info/WHEEL
cluster_shapley-0.1.6.dist-info/top_level.txt
cluster_shapley-0.1.6.dist-info/RECORD
